sparse_convolution/__init__.py
sparse_convolution/sparse_convolution.py
sparse_convolution-0.1.5.dist-info/LICENSE
sparse_convolution-0.1.5.dist-info/METADATA
sparse_convolution-0.1.5.dist-info/WHEEL
sparse_convolution-0.1.5.dist-info/top_level.txt
sparse_convolution-0.1.5.dist-info/RECORD
