Metadata-Version: 2.1
Name: sparse_convolution
Version: 0.1.5
Summary: Sparse convolution in python using Toeplitz convolution matrix multiplication.
Home-page: https://github.com/RichieHakim/sparse_convolution
Author: Richard Hakim
Author-email: richhakim@gmail.com
License: MIT
Keywords: sparse convolution Toeplitz python
Platform: Any
Classifier: Development Status :: 5 - Production/Stable
Classifier: Intended Audience :: Science/Research
Classifier: Topic :: Scientific/Engineering :: Bio-Informatics
Classifier: Programming Language :: Python :: 3
License-File: LICENSE
Requires-Dist: scipy
Requires-Dist: numpy
